{
  "_meta": {
    "label": "English",
    "flag": "🇬🇧"
  },
  "navbar": {
    "overworld": "Overworld",
    "map": "Map",
    "list": "List",
    "reset": "Reset",
    "connected": "Connected",
    "offline": "Offline",
    "dev": "Dev",
    "regions": "Regions",
    "items_broadcast": "📡 Items",
    "regions_broadcast": "📡 Regions",
    "chat": "💬 Chat",
    "ap": "AP",
    "faq": "?",
    "settings": "⚙ Settings"
  },
  "ap_connect": {
    "connect": "Connect to AP",
    "disconnect": "Disconnect AP",
    "bizhawk_connected": "Bizhawk ✓",
    "bizhawk_lua": "Bizhawk Lua",
    "panel_title": "Archipelago Connection",
    "server": "Server",
    "port": "Port",
    "slot_name": "Slot Name",
    "password": "Password (optional)",
    "connecting": "Connecting…",
    "connect_btn": "Connect",
    "error": "Connection failed. Check server/slot/password.",
    "chat_placeholder": "AP Message…"
  },
  "settings": {
    "tabs": {
      "goal": "Goal",
      "dungeons": "Dungeons",
      "locations": "Locations",
      "items": "Items",
      "fusions": "Fusions",
      "qol": "QoL & Tricks",
      "tracker": "Tracker",
      "presets": "Presets"
    },
    "legend": {
      "accessible": "Accessible",
      "out_of_logic": "Out of logic (tricks)",
      "inaccessible": "Inaccessible"
    },
    "goal": {
      "title": "Goal",
      "goal_label": "Goal",
      "defeat_vaati": "Defeat Vaati",
      "pedestal": "Pedestal",
      "dhc_access": "DHC Access",
      "closed": "Closed",
      "open": "Open",
      "pedestal_reward": "Pedestal Reward",
      "none": "None",
      "dhc_big_key": "DHC Big Key",
      "random_item": "Random Item",
      "pedestal_conditions": "Pedestal Conditions",
      "required_elements": "Required Elements (0–4)",
      "required_sword_tier": "Required Sword Tier (0–5)",
      "required_dungeons": "Required Dungeons (0–6)",
      "required_figurines": "Required Figurines (0–136)",
      "starting_hearts": "Starting Hearts (1–20)"
    },
    "dungeons": {
      "dungeon_shuffle": "Dungeon Shuffle",
      "shuffle_elements": "Shuffle Elements",
      "vanilla": "Vanilla",
      "prize": "Prize",
      "anywhere": "Anywhere",
      "small_keys": "Small Keys",
      "own": "Own",
      "big_keys": "Big Keys",
      "dungeon_maps": "Dungeon Maps",
      "start": "Start",
      "compasses": "Compasses",
      "non_element_dungeons": "Non-Element Dungeons",
      "standard": "Standard",
      "excluded": "Excluded",
      "entrance_shuffle": "Entrance Shuffle",
      "dungeon_entrance_shuffle": "Dungeon Entrance Shuffle",
      "no": "No",
      "yes": "Yes",
      "dev_only": "Dev only",
      "entrance_hint": "When enabled, dungeon entrances are shuffled. You can then assign which dungeon each entrance leads to.",
      "dungeon_warps": "Dungeon Warps",
      "warp_none": "None",
      "warp_blue": "Blue",
      "warp_red": "Red",
      "warp_both": "Both"
    },
    "locations": {
      "location_shuffle": "Location Shuffle",
      "rupeesanity": "Rupeesanity",
      "shuffle_pots": "Shuffle Pots",
      "shuffle_digging": "Shuffle Digging",
      "shuffle_underwater": "Shuffle Underwater",
      "gold_enemies": "Gold Enemies",
      "extra_shop_item": "Extra Shop Item",
      "early_weapon": "Early Weapon",
      "biggoron": "Biggoron",
      "disabled": "Disabled",
      "shield": "Shield",
      "mirror_shield": "Mirror Shield",
      "cucco_rounds": "Cucco Rounds (0–10)",
      "goron_sets": "Goron Sets (0–5)",
      "goron_jp_prices": "Goron JP Prices",
      "wind_crests": "Wind Crests",
      "wind_crests_hint": "(unlocked at start)",
      "mt_crenel": "Mt. Crenel",
      "veil_falls": "Veil Falls",
      "cloud_tops": "Cloud Tops",
      "castor_wilds": "Castor Wilds",
      "south_field": "South Field",
      "minish_woods": "Minish Woods"
    },
    "items": {
      "progressive_items": "Progressive Items",
      "progressive_sword": "Progressive Sword",
      "progressive_shield": "Progressive Shield",
      "progressive_bow": "Progressive Bow",
      "progressive_boomerang": "Progressive Boomerang",
      "progressive_scroll": "Progressive Scroll",
      "random_bottle_contents": "Random Bottle Contents",
      "traps_enabled": "Traps Enabled",
      "difficulty": "Difficulty & Weapons",
      "heart_containers": "Heart Containers (0–20)",
      "pieces_of_heart": "Pieces of Heart (0–20)",
      "bomb_bag_required": "Bomb Bag Required",
      "bag_required": "Bag required",
      "free_bombs": "Free bombs",
      "free_plus_bosses": "Free + Bosses",
      "bow_weapon": "Bow = Weapon",
      "gust_jar_weapon": "Gust Jar = Weapon",
      "lantern_weapon": "Lantern = Weapon",
      "no": "No",
      "yes": "Yes"
    },
    "fusions": {
      "fusion_access": "Fusion Access",
      "gold_kinstone": "Gold Kinstone",
      "red_kinstone": "Red Kinstone",
      "blue_kinstone": "Blue Kinstone",
      "green_kinstone": "Green Kinstone",
      "closed": "Closed",
      "vanilla": "Vanilla",
      "combined": "Combined",
      "open": "Open",
      "cloud_multiplier": "Cloud Multiplier ×",
      "swamp_multiplier": "Swamp Multiplier ×"
    },
    "qol": {
      "quality_of_life": "Quality of Life",
      "ocarina_on_select": "Ocarina on Select",
      "boots_on_l": "Boots on L",
      "boots_as_minish": "Boots as Minish",
      "skip_big_octorok": "Skip Big Octorok",
      "tod_boss_door": "ToD Boss Door Replica",
      "tricks": "Tricks",
      "tricks_hint": "(yellow = accessible with tricks)",
      "all": "All",
      "none": "None",
      "no": "No",
      "yes": "Yes"
    },
    "tracker": {
      "tracker_display": "Tracker Display",
      "show_inaccessible": "Show inaccessible locations",
      "inaccessible_hint": "By default, red (inaccessible) locations are hidden in the checklist and left panel. Enabling this option shows them. Map pins are never hidden.",
      "auto_tab_dungeons": "Auto tab — Dungeons",
      "auto_tab_overworld": "Auto tab — Overworld",
      "off": "Off",
      "overview": "Overview",
      "floor": "Floor",
      "on": "On",
      "auto_tab_hint": "Controls whether the map switches automatically when you change area (autotracking / AP). Floor shows individual floor maps in dungeons. Overview shows the full dungeon overview map.",
      "font": "Font",
      "language": "Language",
      "wip_notice": "⚠ This language is not fully translated yet.",
      "logic_source": "Logic Source",
      "ap_world": "AP World",
      "default_logic": "Default Logic",
      "custom_logic": "Custom Logic",
      "import_logic_file": "Import .logic",
      "no_file_loaded": "(no file loaded)",
      "logic_source_hint": "AP World: rules generated from the AP World (default). Default Logic: uses the standalone randomizer's default.logic file. Custom: import your own .logic file."
    }
  },
  "map_areas": {
    "castle": "Castle",
    "clouds": "Clouds",
    "crenel": "Crenel",
    "falls": "Falls",
    "hills": "Hills",
    "hylia": "Hylia",
    "lonlon": "Lon Lon",
    "minishwoods": "Minish Woods",
    "northfield": "N. Field",
    "ruins": "Ruins",
    "southfield": "S. Field",
    "swamp": "Swamp",
    "town": "Town",
    "trilby": "Trilby",
    "valley": "Valley",
    "westernwoods": "W. Woods"
  },
  "checklist": {
    "search_placeholder": "Search…",
    "inaccessible_hidden": "(inaccessible hidden)",
    "visible": "visible",
    "pools": {
      "all": "All",
      "hp": "Hearts",
      "element": "Elements",
      "shop": "Shop",
      "scrub": "Scrub",
      "fairy": "Fairy",
      "scroll": "Scrolls",
      "butterfly": "Butterfly",
      "dig": "Dig",
      "water": "Water",
      "pot": "Pot",
      "enemy": "Enemy",
      "fuse_gold": "Gold Fuse",
      "fuse_red": "Red Fuse",
      "fuse_green": "Green Fuse",
      "fuse_blue": "Blue Fuse",
      "rupee": "Rupee"
    }
  },
  "ap_panel": {
    "chat": "Chat",
    "data": "AP Data",
    "items_received": "Items received",
    "not_connected": "Not connected to AP."
  },
  "faq": {
    "title": "Help & FAQ",
    "links_title": "Links",
    "latest_release": "Latest release",
    "repo_link": "GitHub repository",
    "bizhawk_title": "Bizhawk Connector",
    "bizhawk_desc": "To use Bizhawk autotracking, download the Lua script and load it in Bizhawk (Tools → Lua Console → Script → Open Script). Then click \"Bizhawk Lua\" in the tracker to connect (port 65399).",
    "connector_download": "Download bizhawk_tracker.lua",
    "ap_title": "Archipelago Connection",
    "ap_desc": "Start the tracker, click \"Connect to AP\", enter the server address, port, slot name, and optionally the password."
  },
  "item_grid": {
    "spin_scrolls_active": "Spin Scrolls active",
    "total_hearts": "Total Hearts",
    "wind_element": "Wind Element",
    "fire_element": "Fire Element",
    "water_element": "Water Element",
    "earth_element": "Earth Element",
    "small_key": "Small Key",
    "big_key": "Big Key",
    "map": "Map",
    "compass": "Compass",
    "overworld_locations": "Overworld Locations",
    "dungeon_locations": "{dungeon} Locations",
    "no_locations": "No locations"
  }
}